saintone/__init__.py
saintone/__main__.py
saintone/cli.py
saintone/main.py
saintone/utils.py
saintone-3.0.0.dist-info/licenses/LICENSE
saintone-3.0.0.dist-info/METADATA
saintone-3.0.0.dist-info/WHEEL
saintone-3.0.0.dist-info/entry_points.txt
saintone-3.0.0.dist-info/top_level.txt
saintone-3.0.0.dist-info/RECORD
