Metadata-Version: 2.4
Name: saintone
Version: 3.0.0
Summary: dont download it
Author-email: Anna Wilson <annawilson121990@gmail.com>
Maintainer-email: Anna Wilson <annawilson121990@gmail.com>
License: MIT
Project-URL: bugs, https://github.com/annawilson90/saintone/issues
Project-URL: changelog, https://github.com/annawilson90/saintone/blob/master/changelog.md
Project-URL: homepage, https://github.com/annawilson90/saintone
Requires-Python: >=3.10
License-File: LICENSE
Requires-Dist: typer
Provides-Extra: test
Requires-Dist: coverage; extra == "test"
Requires-Dist: pytest; extra == "test"
Requires-Dist: ruff; extra == "test"
Requires-Dist: ty; extra == "test"
Requires-Dist: ipdb; extra == "test"
Dynamic: license-file
